[
  {
    "ticket_id": "TKT-B88BEC",
    "employee_name": "Swagata",
    "department": "IT",
    "issue_description": "server down",
    "priority": "P1",
    "category": "Incident",
    "status": "Open",
    "created_at": "2026-04-29T10:23:04.360546",
    "resolved_at": null,
    "sla_breached": false
  },
  {
    "ticket_id": "TKT-2B2EC5",
    "employee_name": "Rahul",
    "department": "HR",
    "issue_description": "internet disconnected",
    "priority": "P2",
    "category": "Incident",
    "status": "In Progress",
    "created_at": "2026-04-29T10:23:56.805956",
    "resolved_at": null,
    "sla_breached": false
  },
  {
    "ticket_id": "TKT-98BB22",
    "employee_name": "Priya",
    "department": "Finance",
    "issue_description": "laptop running slow",
    "priority": "P3",
    "category": "Service Request",
    "status": "Open",
    "created_at": "2026-04-29T10:24:29.997935",
    "resolved_at": null,
    "sla_breached": false
  },
  {
    "ticket_id": "TKT-AA0A65",
    "employee_name": "Amit",
    "department": "Admin",
    "issue_description": "password reset",
    "priority": "P4",
    "category": "Service Request",
    "status": "Open",
    "created_at": "2026-04-29T10:24:57.735492",
    "resolved_at": null,
    "sla_breached": false
  }
]